decompilellm/__init__.py
decompilellm/__main__.py
decompilellm/api.py
decompilellm/cli.py
decompilellm/constants.py
decompilellm/decompiler.py
decompilellm/disassembler.py
decompilellm/token_utils.py
decompilellm/utils.py
decompilellm-1.0.1.dist-info/licenses/LICENSE.MD
decompilellm-1.0.1.dist-info/METADATA
decompilellm-1.0.1.dist-info/WHEEL
decompilellm-1.0.1.dist-info/top_level.txt
decompilellm-1.0.1.dist-info/RECORD
