Metadata-Version: 2.4
Name: decompilellm
Version: 1.0.1
Summary: An LLM powered Python decompiler.
License:                     GNU GENERAL PUBLIC LICENSE
Project-URL: Homepage, https://github.com/iancdev/python-decompile-llm
Project-URL: Bug Tracker, https://github.com/iancdev/python-decompile-llm/issues
Classifier: Programming Language :: Python :: 3
Classifier: Operating System :: OS Independent
Requires-Python: >=3.10
License-File: LICENSE.MD
Requires-Dist: annotated-types==0.7.0
Requires-Dist: anyio==4.9.0
Requires-Dist: certifi==2025.4.26
Requires-Dist: charset-normalizer==3.4.2
Requires-Dist: click==8.2.0
Requires-Dist: colorama==0.4.6
Requires-Dist: distro==1.9.0
Requires-Dist: h11==0.16.0
Requires-Dist: httpcore==1.0.9
Requires-Dist: httpx==0.28.1
Requires-Dist: idna==3.10
Requires-Dist: jiter==0.9.0
Requires-Dist: openai==1.78.1
Requires-Dist: pydantic==2.11.4
Requires-Dist: pydantic_core==2.33.2
Requires-Dist: regex==2024.11.6
Requires-Dist: requests==2.32.3
Requires-Dist: six==1.17.0
Requires-Dist: sniffio==1.3.1
Requires-Dist: tiktoken==0.9.0
Requires-Dist: tqdm==4.67.1
Requires-Dist: typing-inspection==0.4.0
Requires-Dist: typing_extensions==4.13.2
Requires-Dist: urllib3==2.4.0
Requires-Dist: xdis==6.1.3
Dynamic: license-file
